2.sav
test.py
ttwl_cli_saveedit-1.0.0.data/data/share/ttwl-cli-saveedit/COPYING.txt
ttwl_cli_saveedit-1.0.0.data/data/share/ttwl-cli-saveedit/README-profile.md
ttwl_cli_saveedit-1.0.0.data/data/share/ttwl-cli-saveedit/README-saves.md
ttwl_cli_saveedit-1.0.0.data/data/share/ttwl-cli-saveedit/README.md
ttwl_cli_saveedit-1.0.0.data/data/share/ttwl-cli-saveedit/item_exports/mod_testing_gear.txt
ttwl_cli_saveedit-1.0.0.data/data/share/ttwl-cli-saveedit/protobufs/OakProfile.proto
ttwl_cli_saveedit-1.0.0.data/data/share/ttwl-cli-saveedit/protobufs/OakSave.proto
ttwl_cli_saveedit-1.0.0.data/data/share/ttwl-cli-saveedit/protobufs/OakShared.proto
ttwl_cli_saveedit-1.0.0.data/data/share/ttwl-cli-saveedit/protobufs/README.md
ttwlsave/OakProfile_pb2.py
ttwlsave/OakSave_pb2.py
ttwlsave/OakShared_pb2.py
ttwlsave/__init__.py
ttwlsave/cli_archive.py
ttwlsave/cli_common.py
ttwlsave/cli_copy_pt.py
ttwlsave/cli_edit.py
ttwlsave/cli_import_json.py
ttwlsave/cli_import_protobuf.py
ttwlsave/cli_info.py
ttwlsave/cli_prof_edit.py
ttwlsave/cli_prof_import_json.py
ttwlsave/cli_prof_import_protobuf.py
ttwlsave/cli_prof_info.py
ttwlsave/datalib.py
ttwlsave/ttwlbase.py
ttwlsave/ttwlprofile.py
ttwlsave/ttwlsave.py
ttwlsave/__pycache__/OakSave_pb2.cpython-38.pyc
ttwlsave/__pycache__/OakShared_pb2.cpython-38.pyc
ttwlsave/__pycache__/__init__.cpython-38.pyc
ttwlsave/__pycache__/datalib.cpython-38.pyc
ttwlsave/__pycache__/ttwlsave.cpython-38.pyc
ttwlsave/resources/balance_name_mapping.json.gz
ttwlsave/resources/balance_name_mapping.json.xz
ttwlsave/resources/balance_to_inv_key.json.gz
ttwlsave/resources/balance_to_inv_key.json.xz
ttwlsave/resources/inventoryserialdb.json.gz
ttwlsave/resources/inventoryserialdb.json.xz
ttwl_cli_saveedit-1.0.0.dist-info/COPYING.txt
ttwl_cli_saveedit-1.0.0.dist-info/METADATA
ttwl_cli_saveedit-1.0.0.dist-info/WHEEL
ttwl_cli_saveedit-1.0.0.dist-info/entry_points.txt
ttwl_cli_saveedit-1.0.0.dist-info/top_level.txt
ttwl_cli_saveedit-1.0.0.dist-info/RECORD
