Metadata-Version: 2.1
Name: ttwl-cli-saveedit
Version: 1.0.0
Summary: Tiny Tina's Wonderlands Savegame Editor
Home-page: https://github.com/abramhindle/ttwl-cli-saveedit
Author: CJ Kucera, Abram Hindle
Author-email: cj@apocalyptech.com, web@softwareprocess.es
License: zlib/libpng
Platform: UNKNOWN
Classifier: Development Status :: 5 - Production/Stable
Classifier: Environment :: Console
Classifier: Intended Audience :: End Users/Desktop
Classifier: License :: OSI Approved :: zlib/libpng License
Classifier: Natural Language :: English
Classifier: Operating System :: OS Independent
Classifier: Programming Language :: Python :: 3
Classifier: Topic :: Games/Entertainment :: First Person Shooters
Classifier: Topic :: Utilities
License-File: COPYING.txt
Requires-Dist: protobuf (>=3.12,~=3.0)
